fastapi_global_variable/__init__.py
fastapi_global_variable/global_variable.py
fastapi_global_variable-0.0.4.dist-info/METADATA
fastapi_global_variable-0.0.4.dist-info/WHEEL
fastapi_global_variable-0.0.4.dist-info/licenses/LICENSE
fastapi_global_variable-0.0.4.dist-info/RECORD
