Metadata-Version: 2.1
Name: fastapi_global_variable
Version: 0.0.4
Summary: FastAPI Global variable
Project-URL: Homepage, https://github.com/megatron-global/fastapi-global-variable
Project-URL: Bug Tracker, https://github.com/megatron-global/fastapi-global-variable/issues
Author-email: Dzung Nguyen <dung@megatron-solutions.com>
License-File: LICENSE
Classifier: License :: OSI Approved :: MIT License
Classifier: Operating System :: OS Independent
Classifier: Programming Language :: Python :: 3
Requires-Python: >=3.10
